cpnest/plot.py
cpnest/parameter.pxd
cpnest/nest2pos.py
cpnest/__init__.py
cpnest/proposal.py
cpnest/model.py
cpnest/cpnest.py
cpnest/utils.py
cpnest/parameter.c
cpnest/parameter.cpython-314-darwin.so
cpnest/NestedSampling.py
cpnest/parameter.pyx
cpnest/sampler.py
cpnest-0.12.0.dist-info/RECORD
cpnest-0.12.0.dist-info/WHEEL
cpnest-0.12.0.dist-info/top_level.txt
cpnest-0.12.0.dist-info/METADATA
cpnest-0.12.0.dist-info/licenses/LICENSE
